auto_feature_extraction/__init__.py
auto_feature_extraction/_nbdev.py
auto_feature_extraction/auto_feature_extraction.py
feature_extraction/__init__.py
feature_extraction/_nbdev.py
feature_extraction/feature_extraction.py
auto_feature_extraction-0.0.1.dist-info/LICENSE
auto_feature_extraction-0.0.1.dist-info/METADATA
auto_feature_extraction-0.0.1.dist-info/WHEEL
auto_feature_extraction-0.0.1.dist-info/entry_points.txt
auto_feature_extraction-0.0.1.dist-info/top_level.txt
auto_feature_extraction-0.0.1.dist-info/RECORD
